zipline/__init__.py
zipline/algorithm.py
zipline/api.py
zipline/errors.py
zipline/protocol.py
zipline/test_algorithms.py
zipline/version.py
zipline/assets/__init__.py
zipline/assets/_assets.c
zipline/assets/_assets.pyx
zipline/assets/_assets.so
zipline/assets/asset_writer.py
zipline/assets/assets.py
zipline/assets/futures.py
zipline/data/__init__.py
zipline/data/_adjustments.c
zipline/data/_adjustments.pyx
zipline/data/_adjustments.so
zipline/data/_equities.c
zipline/data/_equities.pyx
zipline/data/_equities.so
zipline/data/benchmarks.py
zipline/data/loader.py
zipline/data/paths.py
zipline/data/treasuries.py
zipline/data/treasuries_can.py
zipline/data/us_equity_pricing.py
zipline/data/ffc/loaders/_adjustments.c
zipline/data/ffc/loaders/_equities.c
zipline/finance/__init__.py
zipline/finance/blotter.py
zipline/finance/commission.py
zipline/finance/constants.py
zipline/finance/controls.py
zipline/finance/execution.py
zipline/finance/slippage.py
zipline/finance/trading.py
zipline/finance/performance/__init__.py
zipline/finance/performance/period.py
zipline/finance/performance/position.py
zipline/finance/performance/position_tracker.py
zipline/finance/performance/tracker.py
zipline/finance/risk/__init__.py
zipline/finance/risk/cumulative.py
zipline/finance/risk/period.py
zipline/finance/risk/report.py
zipline/finance/risk/risk.py
zipline/gens/__init__.py
zipline/gens/composites.py
zipline/gens/sim_engine.c
zipline/gens/tradesimulation.py
zipline/gens/utils.py
zipline/history/__init__.py
zipline/history/history.py
zipline/history/history_container.py
zipline/lib/__init__.py
zipline/lib/adjusted_array.c
zipline/lib/adjusted_array.pyx
zipline/lib/adjusted_array.so
zipline/lib/adjustment.c
zipline/lib/adjustment.pyx
zipline/lib/adjustment.so
zipline/lib/rank.c
zipline/lib/rank.pyx
zipline/lib/rank.so
zipline/pipeline/__init__.py
zipline/pipeline/classifier.py
zipline/pipeline/engine.py
zipline-0.8.3.dist-info/DESCRIPTION.rst
zipline-0.8.3.dist-info/METADATA
zipline-0.8.3.dist-info/metadata.json
zipline-0.8.3.dist-info/RECORD
zipline-0.8.3.dist-info/top_level.txt
zipline-0.8.3.dist-info/WHEEL
