Metadata-Version: 2.0
Name: zipline
Version: 0.8.3
Summary: A backtester for financial algorithms.
Home-page: http://zipline.io
Author: Quantopian Inc.
Author-email: opensource@quantopian.com
License: Apache 2.0
Platform: UNKNOWN
Classifier: Development Status :: 4 - Beta
Classifier: License :: OSI Approved :: Apache Software License
Classifier: Natural Language :: English
Classifier: Programming Language :: Python
Classifier: Programming Language :: Python :: 2.7
Classifier: Programming Language :: Python :: 3.3
Classifier: Programming Language :: Python :: 3.4
Classifier: Operating System :: OS Independent
Classifier: Intended Audience :: Science/Research
Classifier: Topic :: Office/Business :: Financial
Classifier: Topic :: Scientific/Engineering :: Information Analysis
Classifier: Topic :: System :: Distributed Computing
Requires-Dist: pip (>=7.1.0)
Requires-Dist: Logbook (==0.10.0)
Requires-Dist: pytz (==2015.4)
Requires-Dist: numpy (==1.9.2)
Requires-Dist: scipy (==0.15.1)
Requires-Dist: pandas (==0.16.1)
Requires-Dist: patsy (==0.4.0)
Requires-Dist: statsmodels (==0.6.1)
Requires-Dist: python-dateutil (==2.4.2)
Requires-Dist: six (==1.9.0)
Requires-Dist: requests (==2.7.0)
Requires-Dist: Cython (==0.22.1)
Requires-Dist: cyordereddict (==0.2.2)
Requires-Dist: bottleneck (==1.0.0)
Requires-Dist: contextlib2 (==0.4.0)
Requires-Dist: networkx (==1.9.1)
Requires-Dist: numexpr (==2.4.3)
Requires-Dist: bcolz (==0.10.0)
Requires-Dist: click (==4.0.0)
Requires-Dist: toolz (==0.7.4)
Requires-Dist: sqlalchemy (==1.0.8)
Provides-Extra: all
Requires-Dist: nose (==1.3.7); extra == 'all'
Requires-Dist: nose-parameterized (==0.5.0); extra == 'all'
Requires-Dist: nose-ignore-docstring (==0.2); extra == 'all'
Requires-Dist: nose-timer (==0.5.0); extra == 'all'
Requires-Dist: xlrd (==0.9.4); extra == 'all'
Requires-Dist: MarkupSafe (==0.23); extra == 'all'
Requires-Dist: Jinja2 (==2.7.3); extra == 'all'
Requires-Dist: funcsigs (==0.4); extra == 'all'
Requires-Dist: Pygments (==2.0.2); extra == 'all'
Requires-Dist: alabaster (==0.7.6); extra == 'all'
Requires-Dist: babel (==1.3); extra == 'all'
Requires-Dist: docutils (==0.12); extra == 'all'
Requires-Dist: snowballstemmer (==1.2.0); extra == 'all'
Requires-Dist: sphinx-rtd-theme (==0.1.8); extra == 'all'
Requires-Dist: sphinx (==1.3.1); extra == 'all'
Requires-Dist: pbr (==1.3.0); extra == 'all'
Requires-Dist: mock (==1.3.0); extra == 'all'
Requires-Dist: testfixtures (==4.1.2); extra == 'all'
Requires-Dist: flake8 (==2.4.1); extra == 'all'
Requires-Dist: mccabe (==0.3.1); extra == 'all'
Requires-Dist: pep8 (==1.5.7); extra == 'all'
Requires-Dist: pyflakes (==0.8.1); extra == 'all'
Requires-Dist: pyandoc (==0.0.1); extra == 'all'
Requires-Dist: docopt (==0.6.2); extra == 'all'
Requires-Dist: numpydoc (==0.5); extra == 'all'
Requires-Dist: mistune (==0.7); extra == 'all'
Requires-Dist: certifi (==2015.4.28); extra == 'all'
Requires-Dist: tornado (==4.2.1); extra == 'all'
Requires-Dist: pyparsing (==2.0.3); extra == 'all'
Requires-Dist: matplotlib (==1.4.3); extra == 'all'
Requires-Dist: Markdown (==2.6.2); extra == 'all'
Requires-Dist: futures (==3.0.3); extra == 'all'
Requires-Dist: requests-futures (==0.9.5); extra == 'all'
Requires-Dist: piprot (==0.9.1); extra == 'all'
Requires-Dist: TA-Lib (==0.4.9); extra == 'all'
Provides-Extra: dev
Requires-Dist: nose (==1.3.7); extra == 'dev'
Requires-Dist: nose-parameterized (==0.5.0); extra == 'dev'
Requires-Dist: nose-ignore-docstring (==0.2); extra == 'dev'
Requires-Dist: nose-timer (==0.5.0); extra == 'dev'
Requires-Dist: xlrd (==0.9.4); extra == 'dev'
Requires-Dist: MarkupSafe (==0.23); extra == 'dev'
Requires-Dist: Jinja2 (==2.7.3); extra == 'dev'
Requires-Dist: funcsigs (==0.4); extra == 'dev'
Requires-Dist: Pygments (==2.0.2); extra == 'dev'
Requires-Dist: alabaster (==0.7.6); extra == 'dev'
Requires-Dist: babel (==1.3); extra == 'dev'
Requires-Dist: docutils (==0.12); extra == 'dev'
Requires-Dist: snowballstemmer (==1.2.0); extra == 'dev'
Requires-Dist: sphinx-rtd-theme (==0.1.8); extra == 'dev'
Requires-Dist: sphinx (==1.3.1); extra == 'dev'
Requires-Dist: pbr (==1.3.0); extra == 'dev'
Requires-Dist: mock (==1.3.0); extra == 'dev'
Requires-Dist: testfixtures (==4.1.2); extra == 'dev'
Requires-Dist: flake8 (==2.4.1); extra == 'dev'
Requires-Dist: mccabe (==0.3.1); extra == 'dev'
Requires-Dist: pep8 (==1.5.7); extra == 'dev'
Requires-Dist: pyflakes (==0.8.1); extra == 'dev'
Requires-Dist: pyandoc (==0.0.1); extra == 'dev'
Requires-Dist: docopt (==0.6.2); extra == 'dev'
Requires-Dist: numpydoc (==0.5); extra == 'dev'
Requires-Dist: mistune (==0.7); extra == 'dev'
Requires-Dist: certifi (==2015.4.28); extra == 'dev'
Requires-Dist: tornado (==4.2.1); extra == 'dev'
Requires-Dist: pyparsing (==2.0.3); extra == 'dev'
Requires-Dist: matplotlib (==1.4.3); extra == 'dev'
Requires-Dist: Markdown (==2.6.2); extra == 'dev'
Requires-Dist: futures (==3.0.3); extra == 'dev'
Requires-Dist: requests-futures (==0.9.5); extra == 'dev'
Requires-Dist: piprot (==0.9.1); extra == 'dev'
Provides-Extra: talib
Requires-Dist: TA-Lib (==0.4.9); extra == 'talib'
